cluster_pack/__init__.py
cluster_pack/_version.py
cluster_pack/filesystem.py
cluster_pack/packaging.py
cluster_pack/process.py
cluster_pack/uploader.py
cluster_pack/skein/__init__.py
cluster_pack/skein/_execute_fun.py
cluster_pack/skein/skein_config_builder.py
cluster_pack/skein/skein_launcher.py
cluster_pack/spark/__init__.py
cluster_pack/spark/spark_config_builder.py
cluster_pack-0.3.17.dist-info/LICENSE
cluster_pack-0.3.17.dist-info/METADATA
cluster_pack-0.3.17.dist-info/WHEEL
cluster_pack-0.3.17.dist-info/top_level.txt
cluster_pack-0.3.17.dist-info/RECORD
