Metadata-Version: 2.1
Name: cluster-pack
Version: 0.3.17
Summary: A library on top of pex to make your Python code easily available on a cluster
Home-page: https://github.com/criteo/cluster-pack
Maintainer: Criteo
Maintainer-email: github@criteo.com
License: UNKNOWN
Keywords: hadoop distributed cluster S3 HDFS
Platform: UNKNOWN
Classifier: Development Status :: 4 - Beta
Classifier: Intended Audience :: Developers
Classifier: Intended Audience :: Science/Research
Classifier: Operating System :: POSIX :: Linux
Classifier: Environment :: Console
Classifier: License :: OSI Approved :: Apache Software License
Classifier: Programming Language :: Python :: 3
Classifier: Programming Language :: Python :: 3.9
Classifier: Programming Language :: Python :: 3.10
Classifier: Programming Language :: Python :: 3.11
Classifier: Topic :: Software Development :: Libraries
Requires-Python: >=3.9
License-File: LICENSE
Requires-Dist: cloudpickle
Requires-Dist: pex>=2.1.137
Requires-Dist: pip>=22.0
Requires-Dist: pyarrow
Requires-Dist: fire
Requires-Dist: types-setuptools
Requires-Dist: wheel-filename
Requires-Dist: fsspec<=2025.10.0
Requires-Dist: s3fs<=2025.10.0
Requires-Dist: skein
Requires-Dist: packaging
